README.rst
setup.py
authorize/__init__.py
authorize/address.py
authorize/bank_account.py
authorize/batch.py
authorize/configuration.py
authorize/credit_card.py
authorize/customer.py
authorize/environment.py
authorize/exceptions.py
authorize/recurring.py
authorize/response_parser.py
authorize/schemas.py
authorize/transaction.py
authorize/xml_data.py
authorize/apis/__init__.py
authorize/apis/address_api.py
authorize/apis/authorize_api.py
authorize/apis/bank_account_api.py
authorize/apis/base_api.py
authorize/apis/batch_api.py
authorize/apis/credit_card_api.py
authorize/apis/customer_api.py
authorize/apis/payment_profile_api.py
authorize/apis/recurring_api.py
authorize/apis/transaction_api.py
fio_py_Authorize.egg-info/PKG-INFO
fio_py_Authorize.egg-info/SOURCES.txt
fio_py_Authorize.egg-info/dependency_links.txt
fio_py_Authorize.egg-info/requires.txt
fio_py_Authorize.egg-info/top_level.txt