Metadata-Version: 1.1
Name: fio-py-Authorize
Version: 1.4.0.1
Summary: A full-featured Python API for Authorize.net's AIM, CIM, ARB and Reporting APIs.
Home-page: https://github.com/fulfilio/py-authorize
Author: Vincent Catalano, Fulfil.IO Inc
Author-email: info@fulfil.io
License: MIT
Platform: UNKNOWN
Classifier: Environment :: Console
Classifier: Environment :: Web Environment
Classifier: Intended Audience :: Developers
Classifier: Programming Language :: Python :: 2.7
Classifier: Programming Language :: Python :: 3
Classifier: Programming Language :: Python :: 3.2
Classifier: Programming Language :: Python :: 3.3
Classifier: Programming Language :: Python :: 3.4
Classifier: Programming Language :: Python :: 3.5
Classifier: Programming Language :: Python :: Implementation :: PyPy
Classifier: License :: OSI Approved :: MIT License
Classifier: Topic :: Office/Business :: Financial
Classifier: Topic :: Internet :: WWW/HTTP
